culturalconformity/__init__.py
culturalconformity/frq_over_time.py
culturalconformity/frqs.py
culturalconformity/interactive.py
culturalconformity/interactivetwo.py
culturalconformity/new_interactive.py
culturalconformity/old_interactive.py
culturalconformity/stochastic.py
culturalconformity-0.0.16.dist-info/METADATA
culturalconformity-0.0.16.dist-info/WHEEL
culturalconformity-0.0.16.dist-info/top_level.txt
culturalconformity-0.0.16.dist-info/RECORD
