Metadata-Version: 2.1
Name: culturalconformity
Version: 0.0.16
Summary: Simulations of conformity, anti-conformity, and unbiased frequency-dependent transmission
Home-page: UNKNOWN
Author: Kaleda Denton
License: UNKNOWN
Platform: UNKNOWN
Requires-Dist: numpy
